[{"id":101,"name":"Mr. Kamal","email":"mrkamal@test.com","address":"Gulshan,Dhaka","phone_number":"01502020110"},{"id":102,"name":"Mr. Jamal Islam","email":"mrjamal@test.com","address":"Gulshan,Dhaka","phone_number":"01502020110"},{"id":103,"name":"Mr. Rahim","email":"mrrahim@test.com","address":"Gulshan,Dhaka","phone_number":"01502020110"},{"id":954845,"name":"Blair Bruen MD","email":"daren71@testmail.com","address":"Dhaka","phone_number":"(701)153-2687"},{"id":352879,"name":"Jerod Mueller","email":"trudie47@testmail.com","address":"UK","phone_number":"(835)162-1924x09032"},{"id":504703,"name":"Estevan Fritsch","email":"yreichert@testmail.com","address":"USA","phone_number":"(359)418-5803x07051"},{"id":897872,"name":"Jack Ratke","email":"nhaag@testmail.com","address":"USA","phone_number":"(763)368-8281"},{"id":784984,"name":"Mr. Reuben Cummings","email":"ukeebler@testmail.com","address":"USA","phone_number":"223-397-0096x1033"},{"id":527500,"name":"Jamar O'Conner","email":"nigel.hills@testmail.com","address":"USA","phone_number":"468.646.3878x787"},{"id":252856,"name":"Prof. Domingo Gusikowski","email":"joaquin.barton@testmail.com","address":"UK","phone_number":"882-998-6679x34768"},{"id":487733,"name":"Mr. Halle Funk I","email":"ncarter@testmail.com","address":"USA","phone_number":"671.060.8758x8410"},{"id":714274,"name":"Santiago Schroeder","email":"grady.barton@testmail.com","address":"UK","phone_number":"03592548628"},{"id":735030,"name":"Bernhard Hoppe","email":"dooley.ettie@testmail.com","address":"USA","phone_number":"1-779-895-1858x446"},{"id":767423,"name":"Weldon Koch","email":"gkonopelski@testmail.com","address":"USA","phone_number":"(473)295-9061x4279"},{"id":816759,"name":"Mr. Sid Hoeger III","email":"anika.weber@testmail.com","address":"USA","phone_number":"181-381-9974"},{"id":990790,"name":"Golden Keebler","email":"reymundo.hoeger@testmail.com","address":"USA","phone_number":"796-765-7186x6524"},{"id":772186,"name":"Dr. Vern Bartell","email":"kassulke.brigit@testmail.com","address":"USA","phone_number":"850-429-1789"},{"id":421408,"name":"Keenan Conn","email":"novella89@testmail.com","address":"USA","phone_number":"708.609.6980"}]